fastcc/__init__.py
fastcc/app.py
fastcc/client.py
fastcc/exceptions.py
fastcc/py.typed
fastcc/router.py
fastcc/utilities/__init__.py
fastcc/utilities/analyze.py
fastcc/utilities/constants.py
fastcc/utilities/interpretation.py
fastcc/utilities/mqtt.py
fastcc/utilities/type_aliases.py
fastcc/utilities/type_definitions.py
fastcc/utilities/validation.py
fastcc-4.1.2.dist-info/METADATA
fastcc-4.1.2.dist-info/WHEEL
fastcc-4.1.2.dist-info/top_level.txt
fastcc-4.1.2.dist-info/RECORD
