Metadata-Version: 2.4
Name: fastcc
Version: 4.1.2
Summary: Lightweight, efficient and developer-friendly framework for mqtt communication.
Author-email: "J. Baudisch" <justin.baudisch@hsbi.de>
Maintainer-email: "J. Baudisch" <justin.baudisch@hsbi.de>
Project-URL: Repository, https://github.com/ReMi-HSBI/fastcc
Keywords: mqtt,protobuf,aiomqtt,asyncio,iot
Classifier: Development Status :: 4 - Beta
Classifier: Intended Audience :: Developers
Classifier: Topic :: Software Development
Classifier: Topic :: Communications
Classifier: Programming Language :: Python
Classifier: Programming Language :: Python :: 3.13
Classifier: Programming Language :: Python :: Implementation :: CPython
Classifier: Typing :: Typed
Requires-Python: >=3.12
Requires-Dist: aiomqtt~=2.4.0
Requires-Dist: protobuf~=6.31.1
Provides-Extra: dev
Requires-Dist: ruff~=0.12.8; extra == "dev"
Requires-Dist: mypy~=1.17.1; extra == "dev"
Requires-Dist: Sphinx~=8.2.3; extra == "dev"
Requires-Dist: furo~=2025.7.19; extra == "dev"
Requires-Dist: types-protobuf~=6.30.2.20250809; extra == "dev"
